k8sdc/__init__.py
k8sdc/provider.py
k8sdc/utility.py
k8sdc/commands/__init__.py
k8sdc/commands/client.py
k8sdc/commands/config.py
k8sdc/commands/helm.py
k8sdc/commands/hosts.py
k8sdc/commands/init.py
k8sdc/commands/machine.py
k8sdc/commands/provision.py
k8sdc/commands/pull.py
k8sdc/commands/sol.py
k8sdc/commands/template.py
k8sdc/commands/up.py
k8sdc-0.0.20.data/data/k8sdc/LICENSE
k8sdc-0.0.20.data/data/k8sdc/ansible.cfg
k8sdc-0.0.20.data/data/k8sdc/site.yaml
k8sdc-0.0.20.data/data/k8sdc/charts/as1_artifact_storage/.helmignore
k8sdc-0.0.20.data/data/k8sdc/charts/as1_artifact_storage/Chart.yaml
k8sdc-0.0.20.data/data/k8sdc/charts/as1_artifact_storage/values.yaml
k8sdc-0.0.20.data/data/k8sdc/charts/cm1_cluster_management/.helmignore
k8sdc-0.0.20.data/data/k8sdc/charts/cm1_cluster_management/Chart.yaml
k8sdc-0.0.20.data/data/k8sdc/charts/cm1_cluster_management/values.yaml
k8sdc-0.0.20.data/data/k8sdc/charts/cm1_cluster_management/templates/k8s-dashboard-dp.yaml
k8sdc-0.0.20.data/data/k8sdc/charts/cm1_cluster_management/templates/k8s-dashboard-ingress.yaml
k8sdc-0.0.20.data/data/k8sdc/charts/cm1_cluster_management/templates/k8s-dashboard-svc.yaml
k8sdc-0.0.20.data/data/k8sdc/charts/cs1_cluster_services/.helmignore
k8sdc-0.0.20.data/data/k8sdc/charts/cs1_cluster_services/Chart.yaml
k8sdc-0.0.20.data/data/k8sdc/charts/cs1_cluster_services/values.yaml
k8sdc-0.0.20.data/data/k8sdc/charts/cs1_cluster_services/templates/k8s-dns-dp.yaml
k8sdc-0.0.20.data/data/k8sdc/charts/cs1_cluster_services/templates/k8s-dns-svc.yaml
k8sdc-0.0.20.data/data/k8sdc/charts/cs1_cluster_services/templates/k8s-heapster-dp.yaml
k8sdc-0.0.20.data/data/k8sdc/charts/cs1_cluster_services/templates/k8s-heapster-svc.yaml
k8sdc-0.0.20.data/data/k8sdc/charts/dbs1_distributed_block_storage/.helmignore
k8sdc-0.0.20.data/data/k8sdc/charts/dbs1_distributed_block_storage/Chart.yaml
k8sdc-0.0.20.data/data/k8sdc/charts/dbs1_distributed_block_storage/values.yaml
k8sdc-0.0.20.dist-info/DESCRIPTION.rst
k8sdc-0.0.20.dist-info/METADATA
k8sdc-0.0.20.dist-info/RECORD
k8sdc-0.0.20.dist-info/WHEEL
k8sdc-0.0.20.dist-info/metadata.json
k8sdc-0.0.20.dist-info/top_level.txt
